cursor_wrapped/__init__.py
cursor_wrapped/main.py
cursor_wrapped-1.0.10.dist-info/METADATA
cursor_wrapped-1.0.10.dist-info/WHEEL
cursor_wrapped-1.0.10.dist-info/entry_points.txt
cursor_wrapped-1.0.10.dist-info/RECORD
