Metadata-Version: 2.4
Name: cursor-wrapped
Version: 1.0.10
Summary: Your Cursor IDE year in review - see your AI coding stats for 2025
Project-URL: Homepage, https://github.com/riyapatel25/cursorWrapped
Project-URL: Repository, https://github.com/riyapatel25/cursorWrapped
Author-email: riyapatel <riya.patel@uwaterloo.ca>
License-Expression: MIT
Keywords: ai,analytics,coding,cursor,stats,wrapped,year-in-review
Classifier: Development Status :: 4 - Beta
Classifier: Environment :: Console
Classifier: Intended Audience :: Developers
Classifier: License :: OSI Approved :: MIT License
Classifier: Programming Language :: Python :: 3
Classifier: Programming Language :: Python :: 3.8
Classifier: Programming Language :: Python :: 3.9
Classifier: Programming Language :: Python :: 3.10
Classifier: Programming Language :: Python :: 3.11
Classifier: Programming Language :: Python :: 3.12
Requires-Python: >=3.8
Requires-Dist: pillow>=9.0.0
Requires-Dist: requests>=2.25.0
Requires-Dist: selenium>=4.0.0
